expta/__init__.py
expta/run.py
expta/analysis/__init__.py
expta/analysis/analysis.py
expta/analysis/driver.py
expta/analysis/search.py
expta/data/__init__.py
expta/data/categorize_data.py
expta/data/driver.py
expta/data/store_data.py
expta-0.1.dist-info/LICENSE
expta-0.1.dist-info/METADATA
expta-0.1.dist-info/WHEEL
expta-0.1.dist-info/top_level.txt
expta-0.1.dist-info/RECORD
